[{"id":1,"name":"从","sex":"女","date":"Fri Jul 16 12:30:45 CST 2021","estimator":"张道长","advice":"测试得分28 | 你可真聪明","formWorkType":"B","formWorkName":"大世界"},{"id":2,"name":"a","sex":"女","date":"Fri Jul 16 12:55:40 CST 2021","estimator":"张道长","advice":"测试得分4 | 为啥不显示","formWorkType":"B","formWorkName":"模板3"},{"id":3,"name":"b","sex":"女","date":"Fri Jul 16 13:14:40 CST 2021","estimator":null,"advice":"测试得分14 | 发穷恶","formWorkType":"B","formWorkName":"模板二"},{"id":4,"name":"b","sex":"女","date":"Fri Jul 16 21:11:23 CST 2021","estimator":"李四","advice":"测试得分28 | 稳如狗为","formWorkType":"B","formWorkName":"大世界"},{"id":5,"name":"a","sex":"女","date":"Sun Jul 18 12:43:58 CST 2021","estimator":"张道长","advice":"测试得分0 | ","formWorkType":"A","formWorkName":"迷人"},{"id":6,"name":"从","sex":"女","date":"2021年07月20日 08时37分05秒","estimator":null,"advice":"测试得分5 | 哈哈","formWorkType":"A","formWorkName":"迷人"},{"id":7,"name":"b","sex":"女","date":"2021年07月20日 14时39分58秒","estimator":"李道长","advice":"测试得分23 | 状况良好，多锻炼","formWorkType":"B","formWorkName":"大世界"},{"id":8,"name":"b","sex":"女","date":"2021年07月20日 15时52分55秒","estimator":"李道长","advice":"测试得分20 | 多锻炼","formWorkType":"B","formWorkName":"大世界"},{"id":9,"name":"a","sex":"女","date":"2021年07月21日 09时50分19秒","estimator":"李道长","advice":"测试得分19 | ","formWorkType":"B","formWorkName":"大世界"},{"id":10,"name":"a","sex":"男","date":"2021年07月21日 09时59分49秒","estimator":"李道长","advice":"测试得分14 | 多锻炼","formWorkType":"B","formWorkName":"模板二"}]