[{"id":1,"username":"ert","password":"111","name":"驴打","profession":"医生","birthday":"2014-08-25","speciality":"天天","phone":"17896548324","deleted":0},{"id":8,"username":"1234","password":"1234","name":"李逍遥","profession":"医生","birthday":"2014-08-25","speciality":"4123","phone":"17896548324","deleted":0},{"id":9,"username":"123789","password":"123","name":"123","profession":"医生","birthday":"2014-08-25","speciality":"132","phone":"17896548324","deleted":0},{"id":6,"username":"yue123","password":"321","name":"呜啦啦","profession":"护士","birthday":"2014-08-25","speciality":"打到","phone":"17896548324","deleted":0},{"id":11,"username":"333","password":"111","name":"王","profession":"护工","birthday":"2014-08-25","speciality":"切菜","phone":"17896548324","deleted":0},{"id":12,"username":"123456","password":"111","name":"月","profession":"护工","birthday":"123","speciality":"召唤","phone":"18944","deleted":1},{"id":13,"username":"1231大","password":"1242rasdf","name":"而无法","profession":"护士","birthday":"12412","speciality":"腻","phone":"12332112341","deleted":1},{"id":10,"username":"巍峨","password":"123","name":"李道长","profession":"医生","birthday":"2014-08-25","speciality":"外壳手术","phone":"17898753014","deleted":0},{"id":14,"username":"九九","password":"123456ht","name":"华佗","profession":"医生","birthday":"2014-08-09","speciality":"把脉","phone":"17896548324","deleted":0},{"id":7,"username":"89546","password":"120ww","name":"魏君豪","profession":"医生","birthday":"20021425","speciality":"昏倒","phone":"3562","deleted":1},{"id":15,"username":"儿童合格","password":"34t3etbes","name":"网格","profession":"护工","birthday":"2014-08-14","speciality":"24吧","phone":"13289487574","deleted":0},{"id":2,"username":"2","password":"3","name":"黑啊","profession":"护士","birthday":"30023","speciality":"切菜","phone":"1879854","deleted":1},{"id":4,"username":"123","password":"123","name":"李四","profession":"护士","birthday":"20200502","speciality":"打架","phone":"1894503","deleted":1},{"id":5,"username":"12","password":"111","name":"张三丰","profession":"护士","birthday":"","speciality":"切菜","phone":"112","deleted":1},{"id":16,"username":"123的","password":"123321q","name":"前往","profession":"医生","birthday":"2014-08-14","speciality":"的期望","phone":"13258974521","deleted":0},{"id":17,"username":"022145","password":"0200501yy","name":"啊","profession":"护士","birthday":"2012-01-21","speciality":"q-","phone":"12389563214","deleted":0}]